CHANGELOG.md
LICENSE
MANIFEST.in
README.md
setup.py
benchmark_tests/__init__.py
benchmark_tests/benchmark.py
mongita/__init__.py
mongita/collection.py
mongita/command_cursor.py
mongita/common.py
mongita/cursor.py
mongita/database.py
mongita/errors.py
mongita/mongita_client.py
mongita/mongitasync.py
mongita/read_concern.py
mongita/results.py
mongita/write_concern.py
mongita.egg-info/PKG-INFO
mongita.egg-info/SOURCES.txt
mongita.egg-info/dependency_links.txt
mongita.egg-info/requires.txt
mongita.egg-info/top_level.txt
mongita/engines/__init__.py
mongita/engines/disk_engine.py
mongita/engines/engine_common.py
mongita/engines/memory_engine.py
scripts/mongitasync