Metadata-Version: 2.1
Name: mongita
Version: 1.0.1
Summary: Mongita is a lightweight embedded document database that implements a commonly-used subset of the MongoDB/PyMongo interface.
Home-page: https://github.com/scottrogowski/mongita
Author: Scott Rogowski
Author-email: scottmrogowski@gmail.com
License: UNKNOWN
Download-URL: https://github.com/scottrogowski/mongita/archive/mongita-1.0.1.tar.gz
Platform: UNKNOWN
Classifier: Programming Language :: Python :: 3
Classifier: License :: OSI Approved :: BSD License
Classifier: Operating System :: OS Independent
Requires-Python: >=3.7
